datawhale_core/__init__.py
datawhale_core/main.py
datawhale_core-0.0.2.dist-info/METADATA
datawhale_core-0.0.2.dist-info/WHEEL
datawhale_core-0.0.2.dist-info/licenses/LICENSE
datawhale_core-0.0.2.dist-info/RECORD
